MANIFEST.in
README.md
azure_env.sh
debug_tools.sh
install_tools.sh
setup.cfg
setup.py
csr_azure_guestshell/__init__.py
csr_azure_guestshell/azure_dbg.py
csr_azure_guestshell/csr_azure_guestshell.py
csr_azure_guestshell.egg-info/PKG-INFO
csr_azure_guestshell.egg-info/SOURCES.txt
csr_azure_guestshell.egg-info/dependency_links.txt
csr_azure_guestshell.egg-info/top_level.txt
csr_azure_guestshell/MetadataMgr/__init__.py
csr_azure_guestshell/MetadataMgr/metadata.py
csr_azure_guestshell/TokenMgr/__init__.py
csr_azure_guestshell/TokenMgr/at_command_file
csr_azure_guestshell/TokenMgr/auth-token.service
csr_azure_guestshell/TokenMgr/clear_token.py
csr_azure_guestshell/TokenMgr/token_api.py
csr_azure_guestshell/TokenMgr/token_svr.py
csr_azure_guestshell/bin/capture-interface.py
csr_azure_guestshell/bin/get-metadata.py
csr_azure_guestshell/bin/load-bin-from-storage.py
csr_azure_guestshell/bin/save-config-to-storage.py
csr_azure_guestshell/bin/save-tech-support-to-storage.py
examples/cli.ps1
examples/get-show-cmds.py
waagent/WALinuxAgent-2.2.14.1.6-1.noarch.rpm
waagent/csr_waagent_install.sh