Metadata-Version: 1.1
Name: csr-azure-guestshell
Version: 1.1.4
Summary: A helper library for Cisco guestshell on Azure
Home-page: https://github4-chn.cisco.com/csr1000v-azure/csr_azure_guestshell
Author: Christopher Reder
Author-email: creder@cisco.com
License: MIT
Download-URL: https://github4-chn.cisco.com/csr1000v-azure/csr_azure_guestshell/archive/1.1.4.tar.gz
Keywords: cisco,azure,csr1000v,csr,guestshell
Platform: UNKNOWN
